__init__.py
chordist/__init__.py
chordist/abstract_chord.py
chordist/banjo.py
chordist/chord.py
chordist/cli.py
chordist/constants.py
chordist/guitar.py
chordist/instrument.py
chordist/instrument_chord.py
chordist/lyrics.py
chordist/modifier.py
chordist/note.py
chordist/song.py
chordist/utils.py
chordist-0.4.0.dist-info/licenses/LICENSE
chordist-0.4.0.dist-info/METADATA
chordist-0.4.0.dist-info/WHEEL
chordist-0.4.0.dist-info/entry_points.txt
chordist-0.4.0.dist-info/top_level.txt
chordist-0.4.0.dist-info/RECORD
