Metadata-Version: 2.4
Name: chordist
Version: 0.4.0
Summary: Some helpful stuff for displaying song chords (or just the bare chords) for string instruments.
Author-email: Robert Huselius <robert@huseli.us>
License-Expression: GPL-3.0-only
Project-URL: Homepage, https://github.com/Eboreg/chordist
Project-URL: Issues, https://github.com/Eboreg/chordist/issues
Project-URL: Source, https://github.com/Eboreg/chordist
Classifier: Development Status :: 4 - Beta
Classifier: Environment :: Console
Classifier: Topic :: Artistic Software
Classifier: Topic :: Text Processing
Requires-Python: >=3.10
License-File: LICENSE
Provides-Extra: dev
Requires-Dist: flake8; extra == "dev"
Requires-Dist: ipdb; extra == "dev"
Requires-Dist: ipython; extra == "dev"
Requires-Dist: isort; extra == "dev"
Requires-Dist: pylint; extra == "dev"
Dynamic: license-file
